{
    "AdditionalScanFolders": [
        "/Users/steven/Code/retold/modules/utility/cumulation/docs"
    ],
    "SourceContentCatalog": {
        "URI~CONTENT~FILE://Users/steven/Code/retold/modules/utility/cumulation/.config/code-server/config.yaml": {
            "UUID": "1a60e788-2aba-4171-affc-1465f817ba94",
            "Type": "URI",
            "Hash": "URI~CONTENT~FILE://Users/steven/Code/retold/modules/utility/cumulation/.config/code-server/config.yaml",
            "Path": "FILE://Users/steven/Code/retold/modules/utility/cumulation/.config/code-server/config.yaml",
            "Location": "/Users/steven/Code/retold/modules/utility/cumulation/.config/code-server",
            "Name": "config.yaml",
            "MimeType": "text/yaml",
            "Nature": "text",
            "Format": "yaml",
            "Schema": "Default",
            "Content": false,
            "Labels": [
                "__LABELSET_TYPE",
                "FILE",
                "__LABELSET_ADDRESS",
                ".config",
                "code-server",
                "__LABELSET_NAME",
                "config",
                "__LABELSET_EXTENSION",
                ".yaml",
                "__LABELSET_FILENAME",
                "config.yaml",
                "__LABELSET_FULLPATH",
                "FILE://Users/steven/Code/retold/modules/utility/cumulation/.config/code-server/config.yaml",
                "__LABELSET_FORMAT",
                "yaml",
                "Default"
            ],
            "FSTAT": {
                "Size": 70,
                "Created": "2024-12-13T15:43:46.958Z",
                "Modified": "2024-12-13T15:43:46.958Z",
                "Accessed": "2024-12-13T19:24:56.097Z",
                "Mode": 33188
            }
        },
        "URI~CONTENT~FILE://Users/steven/Code/retold/modules/utility/cumulation/.config/configstore/update-notifier-npm-check-updates.json": {
            "UUID": "bd0233ad-1395-483a-b2ba-cfa02100ec72",
            "Type": "URI",
            "Hash": "URI~CONTENT~FILE://Users/steven/Code/retold/modules/utility/cumulation/.config/configstore/update-notifier-npm-check-updates.json",
            "Path": "FILE://Users/steven/Code/retold/modules/utility/cumulation/.config/configstore/update-notifier-npm-check-updates.json",
            "Location": "/Users/steven/Code/retold/modules/utility/cumulation/.config/configstore",
            "Name": "update-notifier-npm-check-updates.json",
            "MimeType": "application/json",
            "Nature": "application",
            "Format": "json",
            "Schema": "Default",
            "Content": false,
            "Labels": [
                "__LABELSET_TYPE",
                "FILE",
                "__LABELSET_ADDRESS",
                ".config",
                "configstore",
                "__LABELSET_NAME",
                "update",
                "notifier",
                "npm",
                "check",
                "updates",
                "__LABELSET_EXTENSION",
                ".json",
                "__LABELSET_FILENAME",
                "update-notifier-npm-check-updates.json",
                "__LABELSET_FULLPATH",
                "FILE://Users/steven/Code/retold/modules/utility/cumulation/.config/configstore/update-notifier-npm-check-updates.json",
                "__LABELSET_FORMAT",
                "json",
                "Default"
            ],
            "FSTAT": {
                "Size": 55,
                "Created": "2024-12-13T15:43:46.958Z",
                "Modified": "2024-12-13T15:43:46.958Z",
                "Accessed": "2024-12-13T18:52:16.293Z",
                "Mode": 33188
            }
        },
        "URI~CONTENT~FILE://Users/steven/Code/retold/modules/utility/cumulation/.config/configstore/update-notifier-npm.json": {
            "UUID": "147c9175-2451-41c5-a7a4-28ad8854caed",
            "Type": "URI",
            "Hash": "URI~CONTENT~FILE://Users/steven/Code/retold/modules/utility/cumulation/.config/configstore/update-notifier-npm.json",
            "Path": "FILE://Users/steven/Code/retold/modules/utility/cumulation/.config/configstore/update-notifier-npm.json",
            "Location": "/Users/steven/Code/retold/modules/utility/cumulation/.config/configstore",
            "Name": "update-notifier-npm.json",
            "MimeType": "application/json",
            "Nature": "application",
            "Format": "json",
            "Schema": "Default",
            "Content": false,
            "Labels": [
                "__LABELSET_TYPE",
                "FILE",
                "__LABELSET_ADDRESS",
                ".config",
                "configstore",
                "__LABELSET_NAME",
                "update",
                "notifier",
                "npm",
                "__LABELSET_EXTENSION",
                ".json",
                "__LABELSET_FILENAME",
                "update-notifier-npm.json",
                "__LABELSET_FULLPATH",
                "FILE://Users/steven/Code/retold/modules/utility/cumulation/.config/configstore/update-notifier-npm.json",
                "__LABELSET_FORMAT",
                "json",
                "Default"
            ],
            "FSTAT": {
                "Size": 55,
                "Created": "2024-12-13T15:43:46.958Z",
                "Modified": "2024-12-13T15:43:46.958Z",
                "Accessed": "2024-12-13T18:52:16.293Z",
                "Mode": 33188
            }
        },
        "URI~CONTENT~FILE://Users/steven/Code/retold/modules/utility/cumulation/.config/installation/UI-Requirements.md": {
            "UUID": "0e919ba5-a676-421e-b735-53df06ec1c90",
            "Type": "URI",
            "Hash": "URI~CONTENT~FILE://Users/steven/Code/retold/modules/utility/cumulation/.config/installation/UI-Requirements.md",
            "Path": "FILE://Users/steven/Code/retold/modules/utility/cumulation/.config/installation/UI-Requirements.md",
            "Location": "/Users/steven/Code/retold/modules/utility/cumulation/.config/installation",
            "Name": "UI-Requirements.md",
            "MimeType": "text/markdown",
            "Nature": "text",
            "Format": "markdown",
            "Schema": "Default",
            "Content": "# Questions\n\n. What would you like to call your luxury workspace? my_cool_software\n. What would you like the default password for the code editor to be? 123456789\n. What would you like the repository prefix for your docker images and containers to be? luxury\n. What port would you like to expose the code editor on? 12345\n. Would you like the code editor limited to the local device (explicitly mapping the exposed docker port to 127.0.0.1)? Y\n. Would you like me to generate a Dockerfile? Y\n\ta. What would you like the Dockerfile to be called? Dockerfile_LUXURY\n\tb. Would you like to run Stricture on a folder/file? N\n\t    i.   Which file? ./Model.ddl\n\tc. Would you like MySQL in the Docker Environment? N\n\t\ti.   Would you like to expose the MySQL port? Y\n\t\tii.  What port would you like to expose MySQL on? 3306\n\t\tiii. What would you like the default mysql root password to be? 123456789\n\t\tiv.  What would you like the database name to be? luxury_database\n\t\tv.   Would you like to execute a SQL database population script on container creation (the database is created automatically)? N\n\t\tvi.  Which script would you like to run? ./Database-Initialization.sql\n\td. Would you like add-ons to be installed by default to Visual Studio Code? Y\n\t\ti.   hbenl.vscode-mocha-test-adapter (binding for mocha tests to the test explorer)\n\t\tii.  hbenl.test-adapter-converter (mocha test suite conversion)\n\t\tiii. hbenl.vscode-test-explorer (tree view for visualizing and executing tests)\n\t\tiv.  ritwickdey.LiveServer (static html web server)\n\t\tv.   daylerees.rainglow (tons of color themes like the freshest theme: freshcut)\n\t\tvi.  oderwat.indent-rainbow (rainbow-colored indent levels)\n. Would you like me to edit the package.json? Y\n\ta. Docker build statements\n\tb. Mocha tdd test run statements\n\tc. Mocha IDE test configurations\n\n\n\n",
            "Labels": [
                "__LABELSET_TYPE",
                "FILE",
                "__LABELSET_ADDRESS",
                ".config",
                "installation",
                "__LABELSET_NAME",
                "UI",
                "Requirements",
                "__LABELSET_EXTENSION",
                ".md",
                "__LABELSET_FILENAME",
                "UI-Requirements.md",
                "__LABELSET_FULLPATH",
                "FILE://Users/steven/Code/retold/modules/utility/cumulation/.config/installation/UI-Requirements.md",
                "__LABELSET_FORMAT",
                "markdown",
                "Default"
            ],
            "FSTAT": {
                "Size": 1821,
                "Created": "2024-12-13T15:43:46.958Z",
                "Modified": "2024-12-13T15:43:46.958Z",
                "Accessed": "2024-12-13T18:52:16.293Z",
                "Mode": 33188
            }
        },
        "URI~CONTENT~FILE://Users/steven/Code/retold/modules/utility/cumulation/.config/installation/install_luxury_code.js": {
            "UUID": "5ae28c72-669e-4a4b-8582-ab0eb2d12a26",
            "Type": "URI",
            "Hash": "URI~CONTENT~FILE://Users/steven/Code/retold/modules/utility/cumulation/.config/installation/install_luxury_code.js",
            "Path": "FILE://Users/steven/Code/retold/modules/utility/cumulation/.config/installation/install_luxury_code.js",
            "Location": "/Users/steven/Code/retold/modules/utility/cumulation/.config/installation",
            "Name": "install_luxury_code.js",
            "MimeType": "application/javascript",
            "Nature": "application",
            "Format": "javascript",
            "Schema": "Default",
            "Content": false,
            "Labels": [
                "__LABELSET_TYPE",
                "FILE",
                "__LABELSET_ADDRESS",
                ".config",
                "installation",
                "__LABELSET_NAME",
                "install",
                "luxury",
                "code",
                "__LABELSET_EXTENSION",
                ".js",
                "__LABELSET_FILENAME",
                "install_luxury_code.js",
                "__LABELSET_FULLPATH",
                "FILE://Users/steven/Code/retold/modules/utility/cumulation/.config/installation/install_luxury_code.js",
                "__LABELSET_FORMAT",
                "javascript",
                "Default"
            ],
            "FSTAT": {
                "Size": 3646,
                "Created": "2024-12-13T15:43:46.958Z",
                "Modified": "2024-12-13T15:43:46.958Z",
                "Accessed": "2024-12-13T18:52:16.293Z",
                "Mode": 33188
            }
        },
        "URI~CONTENT~FILE://Users/steven/Code/retold/modules/utility/cumulation/.config/installation/install_luxury_default_configuration.json": {
            "UUID": "2102e1db-1512-47e9-8a3a-650bf5fe275e",
            "Type": "URI",
            "Hash": "URI~CONTENT~FILE://Users/steven/Code/retold/modules/utility/cumulation/.config/installation/install_luxury_default_configuration.json",
            "Path": "FILE://Users/steven/Code/retold/modules/utility/cumulation/.config/installation/install_luxury_default_configuration.json",
            "Location": "/Users/steven/Code/retold/modules/utility/cumulation/.config/installation",
            "Name": "install_luxury_default_configuration.json",
            "MimeType": "application/json",
            "Nature": "application",
            "Format": "json",
            "Schema": "Default",
            "Content": false,
            "Labels": [
                "__LABELSET_TYPE",
                "FILE",
                "__LABELSET_ADDRESS",
                ".config",
                "installation",
                "__LABELSET_NAME",
                "install",
                "luxury",
                "default",
                "configuration",
                "__LABELSET_EXTENSION",
                ".json",
                "__LABELSET_FILENAME",
                "install_luxury_default_configuration.json",
                "__LABELSET_FULLPATH",
                "FILE://Users/steven/Code/retold/modules/utility/cumulation/.config/installation/install_luxury_default_configuration.json",
                "__LABELSET_FORMAT",
                "json",
                "Default"
            ],
            "FSTAT": {
                "Size": 1172,
                "Created": "2024-12-13T15:43:46.958Z",
                "Modified": "2024-12-13T15:43:46.958Z",
                "Accessed": "2024-12-13T18:52:16.293Z",
                "Mode": 33188
            }
        },
        "URI~CONTENT~FILE://Users/steven/Code/retold/modules/utility/cumulation/.config/installation/install_luxury_interaction.json": {
            "UUID": "55b0250c-f85a-4217-b2e5-5f3dccc5c1da",
            "Type": "URI",
            "Hash": "URI~CONTENT~FILE://Users/steven/Code/retold/modules/utility/cumulation/.config/installation/install_luxury_interaction.json",
            "Path": "FILE://Users/steven/Code/retold/modules/utility/cumulation/.config/installation/install_luxury_interaction.json",
            "Location": "/Users/steven/Code/retold/modules/utility/cumulation/.config/installation",
            "Name": "install_luxury_interaction.json",
            "MimeType": "application/json",
            "Nature": "application",
            "Format": "json",
            "Schema": "Default",
            "Content": false,
            "Labels": [
                "__LABELSET_TYPE",
                "FILE",
                "__LABELSET_ADDRESS",
                ".config",
                "installation",
                "__LABELSET_NAME",
                "install",
                "luxury",
                "interaction",
                "__LABELSET_EXTENSION",
                ".json",
                "__LABELSET_FILENAME",
                "install_luxury_interaction.json",
                "__LABELSET_FULLPATH",
                "FILE://Users/steven/Code/retold/modules/utility/cumulation/.config/installation/install_luxury_interaction.json",
                "__LABELSET_FORMAT",
                "json",
                "Default"
            ],
            "FSTAT": {
                "Size": 10,
                "Created": "2024-12-13T15:43:46.958Z",
                "Modified": "2024-12-13T15:43:46.958Z",
                "Accessed": "2024-12-13T18:52:16.293Z",
                "Mode": 33188
            }
        },
        "URI~CONTENT~FILE://Users/steven/Code/retold/modules/utility/cumulation/.config/installation/precedent.1.0.5.js": {
            "UUID": "9edb3ed3-71aa-4a52-bbe7-3c20c102855f",
            "Type": "URI",
            "Hash": "URI~CONTENT~FILE://Users/steven/Code/retold/modules/utility/cumulation/.config/installation/precedent.1.0.5.js",
            "Path": "FILE://Users/steven/Code/retold/modules/utility/cumulation/.config/installation/precedent.1.0.5.js",
            "Location": "/Users/steven/Code/retold/modules/utility/cumulation/.config/installation",
            "Name": "precedent.1.0.5.js",
            "MimeType": "application/javascript",
            "Nature": "application",
            "Format": "javascript",
            "Schema": "Default",
            "Content": false,
            "Labels": [
                "__LABELSET_TYPE",
                "FILE",
                "__LABELSET_ADDRESS",
                ".config",
                "installation",
                "__LABELSET_NAME",
                "precedent",
                "1",
                "0",
                "5",
                "__LABELSET_EXTENSION",
                ".js",
                "__LABELSET_FILENAME",
                "precedent.1.0.5.js",
                "__LABELSET_FULLPATH",
                "FILE://Users/steven/Code/retold/modules/utility/cumulation/.config/installation/precedent.1.0.5.js",
                "__LABELSET_FORMAT",
                "javascript",
                "Default"
            ],
            "FSTAT": {
                "Size": 29718,
                "Created": "2024-12-13T15:43:46.958Z",
                "Modified": "2024-12-13T15:43:46.958Z",
                "Accessed": "2024-12-13T18:52:16.293Z",
                "Mode": 33188
            }
        },
        "URI~CONTENT~FILE://Users/steven/Code/retold/modules/utility/cumulation/.config/luxury-extras/.vscode/launch.json": {
            "UUID": "48cdc605-e3cb-43f7-acd4-447d8861f5d2",
            "Type": "URI",
            "Hash": "URI~CONTENT~FILE://Users/steven/Code/retold/modules/utility/cumulation/.config/luxury-extras/.vscode/launch.json",
            "Path": "FILE://Users/steven/Code/retold/modules/utility/cumulation/.config/luxury-extras/.vscode/launch.json",
            "Location": "/Users/steven/Code/retold/modules/utility/cumulation/.config/luxury-extras/.vscode",
            "Name": "launch.json",
            "MimeType": "application/json",
            "Nature": "application",
            "Format": "json",
            "Schema": "Default",
            "Content": false,
            "Labels": [
                "__LABELSET_TYPE",
                "FILE",
                "__LABELSET_ADDRESS",
                ".config",
                "luxury-extras",
                ".vscode",
                "__LABELSET_NAME",
                "launch",
                "__LABELSET_EXTENSION",
                ".json",
                "__LABELSET_FILENAME",
                "launch.json",
                "__LABELSET_FULLPATH",
                "FILE://Users/steven/Code/retold/modules/utility/cumulation/.config/luxury-extras/.vscode/launch.json",
                "__LABELSET_FORMAT",
                "json",
                "Default"
            ],
            "FSTAT": {
                "Size": 1374,
                "Created": "2024-12-13T15:43:46.958Z",
                "Modified": "2024-12-13T15:43:46.958Z",
                "Accessed": "2024-12-13T18:52:16.293Z",
                "Mode": 33188
            }
        },
        "URI~CONTENT~FILE://Users/steven/Code/retold/modules/utility/cumulation/.config/luxury-extras/Dockerfile_LUXURYCode": {
            "UUID": "a410bdbb-16b9-4ef9-8cdc-03882af2bbcb",
            "Type": "URI",
            "Hash": "URI~CONTENT~FILE://Users/steven/Code/retold/modules/utility/cumulation/.config/luxury-extras/Dockerfile_LUXURYCode",
            "Path": "FILE://Users/steven/Code/retold/modules/utility/cumulation/.config/luxury-extras/Dockerfile_LUXURYCode",
            "Location": "/Users/steven/Code/retold/modules/utility/cumulation/.config/luxury-extras",
            "Name": "Dockerfile_LUXURYCode",
            "MimeType": null,
            "Nature": "UNKNOWN",
            "Format": "UNKNOWN",
            "Schema": "Default",
            "Content": false,
            "Labels": [
                "__LABELSET_TYPE",
                "FILE",
                "__LABELSET_ADDRESS",
                ".config",
                "luxury-extras",
                "__LABELSET_NAME",
                "Dockerfile",
                "LUXURYCode",
                "__LABELSET_EXTENSION",
                "",
                "__LABELSET_FILENAME",
                "Dockerfile_LUXURYCode",
                "__LABELSET_FULLPATH",
                "FILE://Users/steven/Code/retold/modules/utility/cumulation/.config/luxury-extras/Dockerfile_LUXURYCode",
                "__LABELSET_FORMAT",
                "UNKNOWN",
                "Default"
            ],
            "FSTAT": {
                "Size": 1449,
                "Created": "2024-12-13T15:43:46.958Z",
                "Modified": "2024-12-13T15:43:46.958Z",
                "Accessed": "2024-12-13T19:24:56.097Z",
                "Mode": 33188
            }
        },
        "URI~CONTENT~FILE://Users/steven/Code/retold/modules/utility/cumulation/.config/luxury-extras/MySQL/Dockerfile_LUXURYCODE_MySQL": {
            "UUID": "808de002-a44f-4482-81d0-8456c70e76f5",
            "Type": "URI",
            "Hash": "URI~CONTENT~FILE://Users/steven/Code/retold/modules/utility/cumulation/.config/luxury-extras/MySQL/Dockerfile_LUXURYCODE_MySQL",
            "Path": "FILE://Users/steven/Code/retold/modules/utility/cumulation/.config/luxury-extras/MySQL/Dockerfile_LUXURYCODE_MySQL",
            "Location": "/Users/steven/Code/retold/modules/utility/cumulation/.config/luxury-extras/MySQL",
            "Name": "Dockerfile_LUXURYCODE_MySQL",
            "MimeType": null,
            "Nature": "UNKNOWN",
            "Format": "UNKNOWN",
            "Schema": "Default",
            "Content": false,
            "Labels": [
                "__LABELSET_TYPE",
                "FILE",
                "__LABELSET_ADDRESS",
                ".config",
                "luxury-extras",
                "MySQL",
                "__LABELSET_NAME",
                "Dockerfile",
                "LUXURYCODE",
                "MySQL",
                "__LABELSET_EXTENSION",
                "",
                "__LABELSET_FILENAME",
                "Dockerfile_LUXURYCODE_MySQL",
                "__LABELSET_FULLPATH",
                "FILE://Users/steven/Code/retold/modules/utility/cumulation/.config/luxury-extras/MySQL/Dockerfile_LUXURYCODE_MySQL",
                "__LABELSET_FORMAT",
                "UNKNOWN",
                "Default"
            ],
            "FSTAT": {
                "Size": 2860,
                "Created": "2024-12-13T15:43:46.958Z",
                "Modified": "2024-12-13T15:43:46.958Z",
                "Accessed": "2024-12-13T19:24:56.097Z",
                "Mode": 33188
            }
        },
        "URI~CONTENT~FILE://Users/steven/Code/retold/modules/utility/cumulation/.config/luxury-extras/MySQL/MySQL-Laden-Entry.sh": {
            "UUID": "f5b27843-72e9-499a-8019-8a45e94d4e20",
            "Type": "URI",
            "Hash": "URI~CONTENT~FILE://Users/steven/Code/retold/modules/utility/cumulation/.config/luxury-extras/MySQL/MySQL-Laden-Entry.sh",
            "Path": "FILE://Users/steven/Code/retold/modules/utility/cumulation/.config/luxury-extras/MySQL/MySQL-Laden-Entry.sh",
            "Location": "/Users/steven/Code/retold/modules/utility/cumulation/.config/luxury-extras/MySQL",
            "Name": "MySQL-Laden-Entry.sh",
            "MimeType": "application/x-sh",
            "Nature": "application",
            "Format": "x-sh",
            "Schema": "Default",
            "Content": false,
            "Labels": [
                "__LABELSET_TYPE",
                "FILE",
                "__LABELSET_ADDRESS",
                ".config",
                "luxury-extras",
                "MySQL",
                "__LABELSET_NAME",
                "MySQL",
                "Laden",
                "Entry",
                "__LABELSET_EXTENSION",
                ".sh",
                "__LABELSET_FILENAME",
                "MySQL-Laden-Entry.sh",
                "__LABELSET_FULLPATH",
                "FILE://Users/steven/Code/retold/modules/utility/cumulation/.config/luxury-extras/MySQL/MySQL-Laden-Entry.sh",
                "__LABELSET_FORMAT",
                "x-sh",
                "Default"
            ],
            "FSTAT": {
                "Size": 247,
                "Created": "2024-12-13T15:43:46.958Z",
                "Modified": "2024-12-13T15:43:46.958Z",
                "Accessed": "2024-12-13T18:52:16.293Z",
                "Mode": 33188
            }
        },
        "URI~CONTENT~FILE://Users/steven/Code/retold/modules/utility/cumulation/.config/luxury-extras/MySQL/MySQL-Security.sql": {
            "UUID": "3b961d52-af79-4264-b42d-b6b1f49c57c1",
            "Type": "URI",
            "Hash": "URI~CONTENT~FILE://Users/steven/Code/retold/modules/utility/cumulation/.config/luxury-extras/MySQL/MySQL-Security.sql",
            "Path": "FILE://Users/steven/Code/retold/modules/utility/cumulation/.config/luxury-extras/MySQL/MySQL-Security.sql",
            "Location": "/Users/steven/Code/retold/modules/utility/cumulation/.config/luxury-extras/MySQL",
            "Name": "MySQL-Security.sql",
            "MimeType": "application/x-sql",
            "Nature": "application",
            "Format": "x-sql",
            "Schema": "Default",
            "Content": false,
            "Labels": [
                "__LABELSET_TYPE",
                "FILE",
                "__LABELSET_ADDRESS",
                ".config",
                "luxury-extras",
                "MySQL",
                "__LABELSET_NAME",
                "MySQL",
                "Security",
                "__LABELSET_EXTENSION",
                ".sql",
                "__LABELSET_FILENAME",
                "MySQL-Security.sql",
                "__LABELSET_FULLPATH",
                "FILE://Users/steven/Code/retold/modules/utility/cumulation/.config/luxury-extras/MySQL/MySQL-Security.sql",
                "__LABELSET_FORMAT",
                "x-sql",
                "Default"
            ],
            "FSTAT": {
                "Size": 164,
                "Created": "2024-12-13T15:43:46.958Z",
                "Modified": "2024-12-13T15:43:46.958Z",
                "Accessed": "2024-12-13T18:52:16.293Z",
                "Mode": 33188
            }
        },
        "URI~CONTENT~FILE://Users/steven/Code/retold/modules/utility/cumulation/.gitignore": {
            "UUID": "996d3509-d3cd-49c4-aafc-e019d1961277",
            "Type": "URI",
            "Hash": "URI~CONTENT~FILE://Users/steven/Code/retold/modules/utility/cumulation/.gitignore",
            "Path": "FILE://Users/steven/Code/retold/modules/utility/cumulation/.gitignore",
            "Location": "/Users/steven/Code/retold/modules/utility/cumulation",
            "Name": ".gitignore",
            "MimeType": null,
            "Nature": "UNKNOWN",
            "Format": "UNKNOWN",
            "Schema": "Default",
            "Content": false,
            "Labels": [
                "__LABELSET_TYPE",
                "FILE",
                "__LABELSET_ADDRESS",
                "__LABELSET_NAME",
                "__LABELSET_EXTENSION",
                "",
                "__LABELSET_FILENAME",
                ".gitignore",
                "__LABELSET_FULLPATH",
                "FILE://Users/steven/Code/retold/modules/utility/cumulation/.gitignore",
                "__LABELSET_FORMAT",
                "UNKNOWN",
                "Default"
            ],
            "FSTAT": {
                "Size": 574,
                "Created": "2024-12-13T15:43:46.958Z",
                "Modified": "2024-12-13T15:43:46.959Z",
                "Accessed": "2024-12-13T18:51:28.357Z",
                "Mode": 33188
            }
        },
        "URI~CONTENT~FILE://Users/steven/Code/retold/modules/utility/cumulation/.travis.yml": {
            "UUID": "8cf4b31d-a1a4-43b5-b7d0-b68b2b3fd556",
            "Type": "URI",
            "Hash": "URI~CONTENT~FILE://Users/steven/Code/retold/modules/utility/cumulation/.travis.yml",
            "Path": "FILE://Users/steven/Code/retold/modules/utility/cumulation/.travis.yml",
            "Location": "/Users/steven/Code/retold/modules/utility/cumulation",
            "Name": ".travis.yml",
            "MimeType": "text/yaml",
            "Nature": "text",
            "Format": "yaml",
            "Schema": "Default",
            "Content": false,
            "Labels": [
                "__LABELSET_TYPE",
                "FILE",
                "__LABELSET_ADDRESS",
                "__LABELSET_NAME",
                "travis",
                "__LABELSET_EXTENSION",
                ".yml",
                "__LABELSET_FILENAME",
                ".travis.yml",
                "__LABELSET_FULLPATH",
                "FILE://Users/steven/Code/retold/modules/utility/cumulation/.travis.yml",
                "__LABELSET_FORMAT",
                "yaml",
                "Default"
            ],
            "FSTAT": {
                "Size": 151,
                "Created": "2024-12-13T15:43:46.959Z",
                "Modified": "2024-12-13T15:43:46.959Z",
                "Accessed": "2024-12-13T19:24:56.098Z",
                "Mode": 33188
            }
        },
        "URI~CONTENT~FILE://Users/steven/Code/retold/modules/utility/cumulation/.vscode/launch.json": {
            "UUID": "6196ff3a-7662-447e-83b2-6dba04a4455c",
            "Type": "URI",
            "Hash": "URI~CONTENT~FILE://Users/steven/Code/retold/modules/utility/cumulation/.vscode/launch.json",
            "Path": "FILE://Users/steven/Code/retold/modules/utility/cumulation/.vscode/launch.json",
            "Location": "/Users/steven/Code/retold/modules/utility/cumulation/.vscode",
            "Name": "launch.json",
            "MimeType": "application/json",
            "Nature": "application",
            "Format": "json",
            "Schema": "Default",
            "Content": false,
            "Labels": [
                "__LABELSET_TYPE",
                "FILE",
                "__LABELSET_ADDRESS",
                ".vscode",
                "__LABELSET_NAME",
                "launch",
                "__LABELSET_EXTENSION",
                ".json",
                "__LABELSET_FILENAME",
                "launch.json",
                "__LABELSET_FULLPATH",
                "FILE://Users/steven/Code/retold/modules/utility/cumulation/.vscode/launch.json",
                "__LABELSET_FORMAT",
                "json",
                "Default"
            ],
            "FSTAT": {
                "Size": 1374,
                "Created": "2024-12-13T15:43:46.959Z",
                "Modified": "2024-12-13T15:43:46.959Z",
                "Accessed": "2024-12-13T18:52:16.293Z",
                "Mode": 33188
            }
        },
        "URI~CONTENT~FILE://Users/steven/Code/retold/modules/utility/cumulation/Dockerfile_LUXURYCode": {
            "UUID": "0e87123b-6ea4-436b-b767-03bf768fb737",
            "Type": "URI",
            "Hash": "URI~CONTENT~FILE://Users/steven/Code/retold/modules/utility/cumulation/Dockerfile_LUXURYCode",
            "Path": "FILE://Users/steven/Code/retold/modules/utility/cumulation/Dockerfile_LUXURYCode",
            "Location": "/Users/steven/Code/retold/modules/utility/cumulation",
            "Name": "Dockerfile_LUXURYCode",
            "MimeType": null,
            "Nature": "UNKNOWN",
            "Format": "UNKNOWN",
            "Schema": "Default",
            "Content": false,
            "Labels": [
                "__LABELSET_TYPE",
                "FILE",
                "__LABELSET_ADDRESS",
                "__LABELSET_NAME",
                "Dockerfile",
                "LUXURYCode",
                "__LABELSET_EXTENSION",
                "",
                "__LABELSET_FILENAME",
                "Dockerfile_LUXURYCode",
                "__LABELSET_FULLPATH",
                "FILE://Users/steven/Code/retold/modules/utility/cumulation/Dockerfile_LUXURYCode",
                "__LABELSET_FORMAT",
                "UNKNOWN",
                "Default"
            ],
            "FSTAT": {
                "Size": 1422,
                "Created": "2024-12-13T15:43:46.959Z",
                "Modified": "2024-12-13T15:43:46.959Z",
                "Accessed": "2024-12-13T19:24:56.098Z",
                "Mode": 33188
            }
        },
        "URI~CONTENT~FILE://Users/steven/Code/retold/modules/utility/cumulation/LICENSE": {
            "UUID": "0dc2d6cc-888e-4cd8-bd13-e48fd6d2746b",
            "Type": "URI",
            "Hash": "URI~CONTENT~FILE://Users/steven/Code/retold/modules/utility/cumulation/LICENSE",
            "Path": "FILE://Users/steven/Code/retold/modules/utility/cumulation/LICENSE",
            "Location": "/Users/steven/Code/retold/modules/utility/cumulation",
            "Name": "LICENSE",
            "MimeType": null,
            "Nature": "UNKNOWN",
            "Format": "UNKNOWN",
            "Schema": "Default",
            "Content": false,
            "Labels": [
                "__LABELSET_TYPE",
                "FILE",
                "__LABELSET_ADDRESS",
                "__LABELSET_NAME",
                "LICENSE",
                "__LABELSET_EXTENSION",
                "",
                "__LABELSET_FILENAME",
                "LICENSE",
                "__LABELSET_FULLPATH",
                "FILE://Users/steven/Code/retold/modules/utility/cumulation/LICENSE",
                "__LABELSET_FORMAT",
                "UNKNOWN",
                "Default"
            ],
            "FSTAT": {
                "Size": 1081,
                "Created": "2024-12-13T15:43:46.959Z",
                "Modified": "2024-12-13T15:43:46.959Z",
                "Accessed": "2024-12-13T19:24:56.098Z",
                "Mode": 33188
            }
        },
        "URI~CONTENT~FILE://Users/steven/Code/retold/modules/utility/cumulation/README.md": {
            "UUID": "6181d6a4-4bd0-4c49-b098-4aa573afd490",
            "Type": "URI",
            "Hash": "URI~CONTENT~FILE://Users/steven/Code/retold/modules/utility/cumulation/README.md",
            "Path": "FILE://Users/steven/Code/retold/modules/utility/cumulation/README.md",
            "Location": "/Users/steven/Code/retold/modules/utility/cumulation",
            "Name": "README.md",
            "MimeType": "text/markdown",
            "Nature": "text",
            "Format": "markdown",
            "Schema": "Default",
            "Content": "# Cumulation\n\n## Building\n\n```\ngulp minified\ngulp debug\n\n(or)\n\n`gulp build`\n\n## Related Packages\n\n- [fable](https://github.com/stevenvelozo/fable) - Application services framework\n\n## License\n\nMIT\n\n## Contributing\n\nPull requests are welcome. For details on our code of conduct, contribution process, and testing requirements, see the [Retold Contributing Guide](https://github.com/stevenvelozo/retold/blob/main/docs/contributing.md).\n",
            "Labels": [
                "__LABELSET_TYPE",
                "FILE",
                "__LABELSET_ADDRESS",
                "__LABELSET_NAME",
                "README",
                "__LABELSET_EXTENSION",
                ".md",
                "__LABELSET_FILENAME",
                "README.md",
                "__LABELSET_FULLPATH",
                "FILE://Users/steven/Code/retold/modules/utility/cumulation/README.md",
                "__LABELSET_FORMAT",
                "markdown",
                "Default"
            ],
            "FSTAT": {
                "Size": 434,
                "Created": "2026-04-09T23:33:45.502Z",
                "Modified": "2026-04-09T23:33:45.502Z",
                "Accessed": "2026-04-09T23:33:45.508Z",
                "Mode": 33188
            }
        },
        "URI~CONTENT~FILE://Users/steven/Code/retold/modules/utility/cumulation/bower.json": {
            "UUID": "860347e2-2f26-4822-9adc-23ad11d30c4a",
            "Type": "URI",
            "Hash": "URI~CONTENT~FILE://Users/steven/Code/retold/modules/utility/cumulation/bower.json",
            "Path": "FILE://Users/steven/Code/retold/modules/utility/cumulation/bower.json",
            "Location": "/Users/steven/Code/retold/modules/utility/cumulation",
            "Name": "bower.json",
            "MimeType": "application/json",
            "Nature": "application",
            "Format": "json",
            "Schema": "Default",
            "Content": false,
            "Labels": [
                "__LABELSET_TYPE",
                "FILE",
                "__LABELSET_ADDRESS",
                "__LABELSET_NAME",
                "bower",
                "__LABELSET_EXTENSION",
                ".json",
                "__LABELSET_FILENAME",
                "bower.json",
                "__LABELSET_FULLPATH",
                "FILE://Users/steven/Code/retold/modules/utility/cumulation/bower.json",
                "__LABELSET_FORMAT",
                "json",
                "Default"
            ],
            "FSTAT": {
                "Size": 468,
                "Created": "2024-12-13T15:43:46.959Z",
                "Modified": "2024-12-13T15:43:46.959Z",
                "Accessed": "2024-12-13T18:52:16.293Z",
                "Mode": 33188
            }
        },
        "URI~CONTENT~FILE://Users/steven/Code/retold/modules/utility/cumulation/dist/cumulation.js": {
            "UUID": "e4553bf3-ca98-4b2a-9d5a-e635d68536f6",
            "Type": "URI",
            "Hash": "URI~CONTENT~FILE://Users/steven/Code/retold/modules/utility/cumulation/dist/cumulation.js",
            "Path": "FILE://Users/steven/Code/retold/modules/utility/cumulation/dist/cumulation.js",
            "Location": "/Users/steven/Code/retold/modules/utility/cumulation/dist",
            "Name": "cumulation.js",
            "MimeType": "application/javascript",
            "Nature": "application",
            "Format": "javascript",
            "Schema": "Default",
            "Content": false,
            "Labels": [
                "__LABELSET_TYPE",
                "FILE",
                "__LABELSET_ADDRESS",
                "dist",
                "__LABELSET_NAME",
                "cumulation",
                "__LABELSET_EXTENSION",
                ".js",
                "__LABELSET_FILENAME",
                "cumulation.js",
                "__LABELSET_FULLPATH",
                "FILE://Users/steven/Code/retold/modules/utility/cumulation/dist/cumulation.js",
                "__LABELSET_FORMAT",
                "javascript",
                "Default"
            ],
            "FSTAT": {
                "Size": 1751868,
                "Created": "2024-12-13T15:43:46.959Z",
                "Modified": "2024-12-13T15:43:46.961Z",
                "Accessed": "2024-12-23T17:17:25.736Z",
                "Mode": 33188
            }
        },
        "URI~CONTENT~FILE://Users/steven/Code/retold/modules/utility/cumulation/dist/cumulation.min.js": {
            "UUID": "ae0504f8-b5c1-4bb0-9cb9-2d2e7f7441c4",
            "Type": "URI",
            "Hash": "URI~CONTENT~FILE://Users/steven/Code/retold/modules/utility/cumulation/dist/cumulation.min.js",
            "Path": "FILE://Users/steven/Code/retold/modules/utility/cumulation/dist/cumulation.min.js",
            "Location": "/Users/steven/Code/retold/modules/utility/cumulation/dist",
            "Name": "cumulation.min.js",
            "MimeType": "application/javascript",
            "Nature": "application",
            "Format": "javascript",
            "Schema": "Default",
            "Content": false,
            "Labels": [
                "__LABELSET_TYPE",
                "FILE",
                "__LABELSET_ADDRESS",
                "dist",
                "__LABELSET_NAME",
                "cumulation",
                "min",
                "__LABELSET_EXTENSION",
                ".js",
                "__LABELSET_FILENAME",
                "cumulation.min.js",
                "__LABELSET_FULLPATH",
                "FILE://Users/steven/Code/retold/modules/utility/cumulation/dist/cumulation.min.js",
                "__LABELSET_FORMAT",
                "javascript",
                "Default"
            ],
            "FSTAT": {
                "Size": 203646,
                "Created": "2024-12-13T15:43:46.961Z",
                "Modified": "2024-12-13T15:43:46.962Z",
                "Accessed": "2024-12-23T17:17:25.739Z",
                "Mode": 33188
            }
        },
        "URI~CONTENT~FILE://Users/steven/Code/retold/modules/utility/cumulation/dist/cumulation.min.js.map": {
            "UUID": "acf80606-7805-4601-9d65-657a4242a20b",
            "Type": "URI",
            "Hash": "URI~CONTENT~FILE://Users/steven/Code/retold/modules/utility/cumulation/dist/cumulation.min.js.map",
            "Path": "FILE://Users/steven/Code/retold/modules/utility/cumulation/dist/cumulation.min.js.map",
            "Location": "/Users/steven/Code/retold/modules/utility/cumulation/dist",
            "Name": "cumulation.min.js.map",
            "MimeType": "application/json",
            "Nature": "application",
            "Format": "json",
            "Schema": "Default",
            "Content": false,
            "Labels": [
                "__LABELSET_TYPE",
                "FILE",
                "__LABELSET_ADDRESS",
                "dist",
                "__LABELSET_NAME",
                "cumulation",
                "min",
                "js",
                "__LABELSET_EXTENSION",
                ".map",
                "__LABELSET_FILENAME",
                "cumulation.min.js.map",
                "__LABELSET_FULLPATH",
                "FILE://Users/steven/Code/retold/modules/utility/cumulation/dist/cumulation.min.js.map",
                "__LABELSET_FORMAT",
                "json",
                "Default"
            ],
            "FSTAT": {
                "Size": 995710,
                "Created": "2024-12-13T15:43:46.962Z",
                "Modified": "2024-12-13T15:43:46.971Z",
                "Accessed": "2024-12-23T17:17:25.740Z",
                "Mode": 33188
            }
        },
        "URI~CONTENT~FILE://Users/steven/Code/retold/modules/utility/cumulation/dist/indoctrinate_content_staging/Indoctrinate-Catalog-AppData.json": {
            "UUID": "7b34c1b5-c7d1-44b4-aa5b-6cedac29f767",
            "Type": "URI",
            "Hash": "URI~CONTENT~FILE://Users/steven/Code/retold/modules/utility/cumulation/dist/indoctrinate_content_staging/Indoctrinate-Catalog-AppData.json",
            "Path": "FILE://Users/steven/Code/retold/modules/utility/cumulation/dist/indoctrinate_content_staging/Indoctrinate-Catalog-AppData.json",
            "Location": "/Users/steven/Code/retold/modules/utility/cumulation/dist/indoctrinate_content_staging",
            "Name": "Indoctrinate-Catalog-AppData.json",
            "MimeType": "application/json",
            "Nature": "application",
            "Format": "json",
            "Schema": "Default",
            "Content": false,
            "Labels": [
                "__LABELSET_TYPE",
                "FILE",
                "__LABELSET_ADDRESS",
                "dist",
                "indoctrinate_content_staging",
                "__LABELSET_NAME",
                "Indoctrinate",
                "Catalog",
                "AppData",
                "__LABELSET_EXTENSION",
                ".json",
                "__LABELSET_FILENAME",
                "Indoctrinate-Catalog-AppData.json",
                "__LABELSET_FULLPATH",
                "FILE://Users/steven/Code/retold/modules/utility/cumulation/dist/indoctrinate_content_staging/Indoctrinate-Catalog-AppData.json",
                "__LABELSET_FORMAT",
                "json",
                "Default"
            ],
            "FSTAT": {
                "Size": 502,
                "Created": "2026-04-09T23:33:45.506Z",
                "Modified": "2026-04-10T02:06:14.642Z",
                "Accessed": "2026-04-10T01:55:37.488Z",
                "Mode": 33188
            }
        },
        "URI~CONTENT~FILE://Users/steven/Code/retold/modules/utility/cumulation/docs/.nojekyll": {
            "UUID": "1e4492f4-f743-40c8-8b25-dafb927fa6d7",
            "Type": "URI",
            "Hash": "URI~CONTENT~FILE://Users/steven/Code/retold/modules/utility/cumulation/docs/.nojekyll",
            "Path": "FILE://Users/steven/Code/retold/modules/utility/cumulation/docs/.nojekyll",
            "Location": "/Users/steven/Code/retold/modules/utility/cumulation/docs",
            "Name": ".nojekyll",
            "MimeType": null,
            "Nature": "UNKNOWN",
            "Format": "UNKNOWN",
            "Schema": "Default",
            "Content": false,
            "Labels": [
                "__LABELSET_TYPE",
                "FILE",
                "__LABELSET_ADDRESS",
                "docs",
                "__LABELSET_NAME",
                "__LABELSET_EXTENSION",
                "",
                "__LABELSET_FILENAME",
                ".nojekyll",
                "__LABELSET_FULLPATH",
                "FILE://Users/steven/Code/retold/modules/utility/cumulation/docs/.nojekyll",
                "__LABELSET_FORMAT",
                "UNKNOWN",
                "Default"
            ],
            "FSTAT": {
                "Created": "2026-04-09T23:33:45.506Z",
                "Modified": "2026-04-10T01:50:32.899Z",
                "Accessed": "2026-04-09T23:33:45.506Z",
                "Mode": 33188
            }
        },
        "URI~CONTENT~FILE://Users/steven/Code/retold/modules/utility/cumulation/docs/_version.json": {
            "UUID": "74af5c6e-a3ff-48cd-8040-037ae753fd6c",
            "Type": "URI",
            "Hash": "URI~CONTENT~FILE://Users/steven/Code/retold/modules/utility/cumulation/docs/_version.json",
            "Path": "FILE://Users/steven/Code/retold/modules/utility/cumulation/docs/_version.json",
            "Location": "/Users/steven/Code/retold/modules/utility/cumulation/docs",
            "Name": "_version.json",
            "MimeType": "application/json",
            "Nature": "application",
            "Format": "json",
            "Schema": "Default",
            "Content": false,
            "Labels": [
                "__LABELSET_TYPE",
                "FILE",
                "__LABELSET_ADDRESS",
                "docs",
                "__LABELSET_NAME",
                "version",
                "__LABELSET_EXTENSION",
                ".json",
                "__LABELSET_FILENAME",
                "_version.json",
                "__LABELSET_FULLPATH",
                "FILE://Users/steven/Code/retold/modules/utility/cumulation/docs/_version.json",
                "__LABELSET_FORMAT",
                "json",
                "Default"
            ],
            "FSTAT": {
                "Size": 165,
                "Created": "2026-04-10T01:50:32.845Z",
                "Modified": "2026-04-10T01:50:32.845Z",
                "Accessed": "2026-04-10T01:50:32.933Z",
                "Mode": 33188
            }
        },
        "URI~CONTENT~FILE://Users/steven/Code/retold/modules/utility/cumulation/docs/css/docuserve.css": {
            "UUID": "7e615ee9-27d4-4be4-ab98-3de44af3c871",
            "Type": "URI",
            "Hash": "URI~CONTENT~FILE://Users/steven/Code/retold/modules/utility/cumulation/docs/css/docuserve.css",
            "Path": "FILE://Users/steven/Code/retold/modules/utility/cumulation/docs/css/docuserve.css",
            "Location": "/Users/steven/Code/retold/modules/utility/cumulation/docs/css",
            "Name": "docuserve.css",
            "MimeType": "text/css",
            "Nature": "text",
            "Format": "css",
            "Schema": "Default",
            "Content": false,
            "Labels": [
                "__LABELSET_TYPE",
                "FILE",
                "__LABELSET_ADDRESS",
                "docs",
                "css",
                "__LABELSET_NAME",
                "docuserve",
                "__LABELSET_EXTENSION",
                ".css",
                "__LABELSET_FILENAME",
                "docuserve.css",
                "__LABELSET_FULLPATH",
                "FILE://Users/steven/Code/retold/modules/utility/cumulation/docs/css/docuserve.css",
                "__LABELSET_FORMAT",
                "css",
                "Default"
            ],
            "FSTAT": {
                "Size": 1263,
                "Created": "2026-03-10T18:01:03.404Z",
                "Modified": "2026-04-10T01:50:32.895Z",
                "Accessed": "2026-04-10T01:50:34.038Z",
                "Mode": 33188
            }
        },
        "URI~CONTENT~FILE://Users/steven/Code/retold/modules/utility/cumulation/docs/index.html": {
            "UUID": "9a57fc95-1cf1-4e01-9a92-4dcbbc963f14",
            "Type": "URI",
            "Hash": "URI~CONTENT~FILE://Users/steven/Code/retold/modules/utility/cumulation/docs/index.html",
            "Path": "FILE://Users/steven/Code/retold/modules/utility/cumulation/docs/index.html",
            "Location": "/Users/steven/Code/retold/modules/utility/cumulation/docs",
            "Name": "index.html",
            "MimeType": "text/html",
            "Nature": "text",
            "Format": "html",
            "Schema": "Default",
            "Content": false,
            "Labels": [
                "__LABELSET_TYPE",
                "FILE",
                "__LABELSET_ADDRESS",
                "docs",
                "__LABELSET_NAME",
                "index",
                "__LABELSET_EXTENSION",
                ".html",
                "__LABELSET_FILENAME",
                "index.html",
                "__LABELSET_FULLPATH",
                "FILE://Users/steven/Code/retold/modules/utility/cumulation/docs/index.html",
                "__LABELSET_FORMAT",
                "html",
                "Default"
            ],
            "FSTAT": {
                "Size": 1698,
                "Created": "2026-03-10T18:01:03.421Z",
                "Modified": "2026-04-10T01:50:32.898Z",
                "Accessed": "2026-04-10T01:50:34.038Z",
                "Mode": 33188
            }
        },
        "URI~CONTENT~FILE://Users/steven/Code/retold/modules/utility/cumulation/docs/retold-catalog.json": {
            "UUID": "38e330fd-b83e-49f7-809f-d41730da0ee3",
            "Type": "URI",
            "Hash": "URI~CONTENT~FILE://Users/steven/Code/retold/modules/utility/cumulation/docs/retold-catalog.json",
            "Path": "FILE://Users/steven/Code/retold/modules/utility/cumulation/docs/retold-catalog.json",
            "Location": "/Users/steven/Code/retold/modules/utility/cumulation/docs",
            "Name": "retold-catalog.json",
            "MimeType": "application/json",
            "Nature": "application",
            "Format": "json",
            "Schema": "Default",
            "Content": false,
            "Labels": [
                "__LABELSET_TYPE",
                "FILE",
                "__LABELSET_ADDRESS",
                "docs",
                "__LABELSET_NAME",
                "retold",
                "catalog",
                "__LABELSET_EXTENSION",
                ".json",
                "__LABELSET_FILENAME",
                "retold-catalog.json",
                "__LABELSET_FULLPATH",
                "FILE://Users/steven/Code/retold/modules/utility/cumulation/docs/retold-catalog.json",
                "__LABELSET_FORMAT",
                "json",
                "Default"
            ],
            "FSTAT": {
                "Size": 1958,
                "Created": "2026-04-09T23:33:45.507Z",
                "Modified": "2026-04-10T02:06:14.425Z",
                "Accessed": "2026-04-10T01:50:34.038Z",
                "Mode": 33188
            }
        },
        "URI~CONTENT~FILE://Users/steven/Code/retold/modules/utility/cumulation/docs/retold-keyword-index.json": {
            "UUID": "3e287388-ca61-4959-8205-daf4c4ddb533",
            "Type": "URI",
            "Hash": "URI~CONTENT~FILE://Users/steven/Code/retold/modules/utility/cumulation/docs/retold-keyword-index.json",
            "Path": "FILE://Users/steven/Code/retold/modules/utility/cumulation/docs/retold-keyword-index.json",
            "Location": "/Users/steven/Code/retold/modules/utility/cumulation/docs",
            "Name": "retold-keyword-index.json",
            "MimeType": "application/json",
            "Nature": "application",
            "Format": "json",
            "Schema": "Default",
            "Content": false,
            "Labels": [
                "__LABELSET_TYPE",
                "FILE",
                "__LABELSET_ADDRESS",
                "docs",
                "__LABELSET_NAME",
                "retold",
                "keyword",
                "index",
                "__LABELSET_EXTENSION",
                ".json",
                "__LABELSET_FILENAME",
                "retold-keyword-index.json",
                "__LABELSET_FULLPATH",
                "FILE://Users/steven/Code/retold/modules/utility/cumulation/docs/retold-keyword-index.json",
                "__LABELSET_FORMAT",
                "json",
                "Default"
            ],
            "FSTAT": {
                "Size": 269,
                "Created": "2026-04-09T23:33:45.507Z",
                "Modified": "2026-04-10T01:50:32.827Z",
                "Accessed": "2026-04-10T01:50:34.038Z",
                "Mode": 33188
            }
        },
        "URI~CONTENT~FILE://Users/steven/Code/retold/modules/utility/cumulation/gulpfile.js": {
            "UUID": "5507838a-83c4-4281-9e3e-7e1a5b1221ca",
            "Type": "URI",
            "Hash": "URI~CONTENT~FILE://Users/steven/Code/retold/modules/utility/cumulation/gulpfile.js",
            "Path": "FILE://Users/steven/Code/retold/modules/utility/cumulation/gulpfile.js",
            "Location": "/Users/steven/Code/retold/modules/utility/cumulation",
            "Name": "gulpfile.js",
            "MimeType": "application/javascript",
            "Nature": "application",
            "Format": "javascript",
            "Schema": "Default",
            "Content": false,
            "Labels": [
                "__LABELSET_TYPE",
                "FILE",
                "__LABELSET_ADDRESS",
                "__LABELSET_NAME",
                "gulpfile",
                "__LABELSET_EXTENSION",
                ".js",
                "__LABELSET_FILENAME",
                "gulpfile.js",
                "__LABELSET_FULLPATH",
                "FILE://Users/steven/Code/retold/modules/utility/cumulation/gulpfile.js",
                "__LABELSET_FORMAT",
                "javascript",
                "Default"
            ],
            "FSTAT": {
                "Size": 1793,
                "Created": "2024-12-13T15:43:46.971Z",
                "Modified": "2024-12-13T15:43:46.971Z",
                "Accessed": "2024-12-13T18:52:16.293Z",
                "Mode": 33188
            }
        },
        "URI~CONTENT~FILE://Users/steven/Code/retold/modules/utility/cumulation/package.json": {
            "UUID": "6700513c-0fb3-427d-a85c-97db85fb9ded",
            "Type": "URI",
            "Hash": "URI~CONTENT~FILE://Users/steven/Code/retold/modules/utility/cumulation/package.json",
            "Path": "FILE://Users/steven/Code/retold/modules/utility/cumulation/package.json",
            "Location": "/Users/steven/Code/retold/modules/utility/cumulation",
            "Name": "package.json",
            "MimeType": "application/json",
            "Nature": "application",
            "Format": "json",
            "Schema": "PackageDotJSON",
            "Content": {
                "name": "cumulation",
                "version": "1.0.18",
                "description": "Cumulation data sync library.",
                "main": "source/Cumulation.js",
                "scripts": {
                    "start": "node source/Cumulation.js",
                    "coverage": "./node_modules/istanbul/lib/cli.js cover ./node_modules/mocha/bin/_mocha -- -u tdd -R spec",
                    "docker-dev-build-image": "docker build ./ -f Dockerfile_LUXURYCode -t retold/cumulation:local",
                    "docker-dev-run": "docker run -it -d --name cumulation-dev -p 127.0.0.1:12340:8080 -p 12306:3306 -p 8086:8086 -v \"$PWD/.config:/home/coder/.config\"  -v \"$PWD:/home/coder/cumulation\" -u \"$(id -u):$(id -g)\" -e \"DOCKER_USER=$USER\" retold/cumulation:local",
                    "docker-dev-run-with-library": "docker run -it -d --name cumulation-dev -p 127.0.0.1:12121:8080 -v \"$PWD/.config:/home/coder/.config\"  -v \"$PWD:/home/coder/retold-dev/cumulation\" -v \"$npm_config_library:/home/coder/retold-dev/library\" -u \"$(id -u):$(id -g)\" -e \"DOCKER_USER=$USER\" retold/cumulation:local",
                    "test": "./node_modules/mocha/bin/_mocha -u tdd -R spec"
                },
                "repository": {
                    "type": "git",
                    "url": "git+https://stevenvelozo@github.com/stevenvelozo/cumulation.git"
                },
                "author": "steven velozo <steven@velozo.com>",
                "license": "MIT",
                "bugs": {
                    "url": "https://github.com/stevenvelozo/cumulation/issues"
                },
                "mocha": {
                    "diff": true,
                    "extension": [
                        "js"
                    ],
                    "package": "./package.json",
                    "reporter": "spec",
                    "slow": "75",
                    "timeout": "5000",
                    "ui": "tdd",
                    "watch-files": [
                        "source/**/*.js",
                        "test/**/*.js"
                    ],
                    "watch-ignore": [
                        "lib/vendor"
                    ]
                },
                "homepage": "https://github.com/stevenvelozo/cumulation#readme",
                "devDependencies": {
                    "babel-core": "^6.26.3",
                    "browserify": "^16.2.2",
                    "chai": "4.1.2",
                    "gulp": "^3.9.1",
                    "gulp-babel": "^7.0.1",
                    "gulp-sourcemaps": "^2.6.4",
                    "gulp-terser": "^1.0.1",
                    "gulp-util": "^3.0.8",
                    "istanbul": "0.4.5",
                    "jsdom": "^11.11.0",
                    "mocha": "5.2.0",
                    "vinyl-buffer": "^1.0.1",
                    "vinyl-source-stream": "^2.0.0"
                },
                "dependencies": {
                    "async": "^2.6.1",
                    "cookie": "^0.3.1",
                    "matilde": "^1.0.0",
                    "moment": "^2.22.2",
                    "simple-get": "^3.0.2",
                    "underscore": "^1.9.1"
                }
            },
            "Labels": [
                "__LABELSET_TYPE",
                "FILE",
                "__LABELSET_ADDRESS",
                "__LABELSET_NAME",
                "package",
                "__LABELSET_EXTENSION",
                ".json",
                "__LABELSET_FILENAME",
                "package.json",
                "__LABELSET_FULLPATH",
                "FILE://Users/steven/Code/retold/modules/utility/cumulation/package.json",
                "__LABELSET_FORMAT",
                "json",
                "PackageDotJSON"
            ],
            "FSTAT": {
                "Size": 2259,
                "Created": "2024-12-13T15:43:46.971Z",
                "Modified": "2024-12-13T15:43:46.971Z",
                "Accessed": "2024-12-13T18:52:16.293Z",
                "Mode": 33188
            }
        },
        "URI~CONTENT~FILE://Users/steven/Code/retold/modules/utility/cumulation/source/Cumulation-Browser-Shim.js": {
            "UUID": "d34df63e-59e1-4521-b298-c00aa519d7e1",
            "Type": "URI",
            "Hash": "URI~CONTENT~FILE://Users/steven/Code/retold/modules/utility/cumulation/source/Cumulation-Browser-Shim.js",
            "Path": "FILE://Users/steven/Code/retold/modules/utility/cumulation/source/Cumulation-Browser-Shim.js",
            "Location": "/Users/steven/Code/retold/modules/utility/cumulation/source",
            "Name": "Cumulation-Browser-Shim.js",
            "MimeType": "application/javascript",
            "Nature": "application",
            "Format": "javascript",
            "Schema": "Default",
            "Content": false,
            "Labels": [
                "__LABELSET_TYPE",
                "FILE",
                "__LABELSET_ADDRESS",
                "source",
                "__LABELSET_NAME",
                "Cumulation",
                "Browser",
                "Shim",
                "__LABELSET_EXTENSION",
                ".js",
                "__LABELSET_FILENAME",
                "Cumulation-Browser-Shim.js",
                "__LABELSET_FULLPATH",
                "FILE://Users/steven/Code/retold/modules/utility/cumulation/source/Cumulation-Browser-Shim.js",
                "__LABELSET_FORMAT",
                "javascript",
                "Default"
            ],
            "FSTAT": {
                "Size": 318,
                "Created": "2024-12-13T15:43:46.971Z",
                "Modified": "2024-12-13T15:43:46.971Z",
                "Accessed": "2024-12-13T18:52:16.293Z",
                "Mode": 33188
            }
        },
        "URI~CONTENT~FILE://Users/steven/Code/retold/modules/utility/cumulation/source/Cumulation-Log.js": {
            "UUID": "b77c9d5e-f14b-4ec9-9421-2b6d6f2eb543",
            "Type": "URI",
            "Hash": "URI~CONTENT~FILE://Users/steven/Code/retold/modules/utility/cumulation/source/Cumulation-Log.js",
            "Path": "FILE://Users/steven/Code/retold/modules/utility/cumulation/source/Cumulation-Log.js",
            "Location": "/Users/steven/Code/retold/modules/utility/cumulation/source",
            "Name": "Cumulation-Log.js",
            "MimeType": "application/javascript",
            "Nature": "application",
            "Format": "javascript",
            "Schema": "Default",
            "Content": false,
            "Labels": [
                "__LABELSET_TYPE",
                "FILE",
                "__LABELSET_ADDRESS",
                "source",
                "__LABELSET_NAME",
                "Cumulation",
                "Log",
                "__LABELSET_EXTENSION",
                ".js",
                "__LABELSET_FILENAME",
                "Cumulation-Log.js",
                "__LABELSET_FULLPATH",
                "FILE://Users/steven/Code/retold/modules/utility/cumulation/source/Cumulation-Log.js",
                "__LABELSET_FORMAT",
                "javascript",
                "Default"
            ],
            "FSTAT": {
                "Size": 1726,
                "Created": "2024-12-13T15:43:46.971Z",
                "Modified": "2024-12-13T15:43:46.972Z",
                "Accessed": "2024-12-13T18:52:16.293Z",
                "Mode": 33188
            }
        },
        "URI~CONTENT~FILE://Users/steven/Code/retold/modules/utility/cumulation/source/Cumulation-Settings-Default.js": {
            "UUID": "7468b951-9cec-4f66-b346-756aae74aab7",
            "Type": "URI",
            "Hash": "URI~CONTENT~FILE://Users/steven/Code/retold/modules/utility/cumulation/source/Cumulation-Settings-Default.js",
            "Path": "FILE://Users/steven/Code/retold/modules/utility/cumulation/source/Cumulation-Settings-Default.js",
            "Location": "/Users/steven/Code/retold/modules/utility/cumulation/source",
            "Name": "Cumulation-Settings-Default.js",
            "MimeType": "application/javascript",
            "Nature": "application",
            "Format": "javascript",
            "Schema": "Default",
            "Content": false,
            "Labels": [
                "__LABELSET_TYPE",
                "FILE",
                "__LABELSET_ADDRESS",
                "source",
                "__LABELSET_NAME",
                "Cumulation",
                "Settings",
                "Default",
                "__LABELSET_EXTENSION",
                ".js",
                "__LABELSET_FILENAME",
                "Cumulation-Settings-Default.js",
                "__LABELSET_FULLPATH",
                "FILE://Users/steven/Code/retold/modules/utility/cumulation/source/Cumulation-Settings-Default.js",
                "__LABELSET_FORMAT",
                "javascript",
                "Default"
            ],
            "FSTAT": {
                "Size": 626,
                "Created": "2024-12-13T15:43:46.972Z",
                "Modified": "2024-12-13T15:43:46.972Z",
                "Accessed": "2024-12-13T18:52:16.293Z",
                "Mode": 33188
            }
        },
        "URI~CONTENT~FILE://Users/steven/Code/retold/modules/utility/cumulation/source/Cumulation.js": {
            "UUID": "abfe9aa7-48c3-4283-b1d4-90ee5e810e7f",
            "Type": "URI",
            "Hash": "URI~CONTENT~FILE://Users/steven/Code/retold/modules/utility/cumulation/source/Cumulation.js",
            "Path": "FILE://Users/steven/Code/retold/modules/utility/cumulation/source/Cumulation.js",
            "Location": "/Users/steven/Code/retold/modules/utility/cumulation/source",
            "Name": "Cumulation.js",
            "MimeType": "application/javascript",
            "Nature": "application",
            "Format": "javascript",
            "Schema": "Default",
            "Content": false,
            "Labels": [
                "__LABELSET_TYPE",
                "FILE",
                "__LABELSET_ADDRESS",
                "source",
                "__LABELSET_NAME",
                "Cumulation",
                "__LABELSET_EXTENSION",
                ".js",
                "__LABELSET_FILENAME",
                "Cumulation.js",
                "__LABELSET_FULLPATH",
                "FILE://Users/steven/Code/retold/modules/utility/cumulation/source/Cumulation.js",
                "__LABELSET_FORMAT",
                "javascript",
                "Default"
            ],
            "FSTAT": {
                "Size": 10443,
                "Created": "2024-12-13T15:43:46.972Z",
                "Modified": "2024-12-13T15:43:46.972Z",
                "Accessed": "2024-12-13T18:52:16.293Z",
                "Mode": 33188
            }
        },
        "URI~CONTENT~FILE://Users/steven/Code/retold/modules/utility/cumulation/source/graph/Cumulation-GraphGet.js": {
            "UUID": "9c344120-1897-4f27-8fd2-153f3d461b0f",
            "Type": "URI",
            "Hash": "URI~CONTENT~FILE://Users/steven/Code/retold/modules/utility/cumulation/source/graph/Cumulation-GraphGet.js",
            "Path": "FILE://Users/steven/Code/retold/modules/utility/cumulation/source/graph/Cumulation-GraphGet.js",
            "Location": "/Users/steven/Code/retold/modules/utility/cumulation/source/graph",
            "Name": "Cumulation-GraphGet.js",
            "MimeType": "application/javascript",
            "Nature": "application",
            "Format": "javascript",
            "Schema": "Default",
            "Content": false,
            "Labels": [
                "__LABELSET_TYPE",
                "FILE",
                "__LABELSET_ADDRESS",
                "source",
                "graph",
                "__LABELSET_NAME",
                "Cumulation",
                "GraphGet",
                "__LABELSET_EXTENSION",
                ".js",
                "__LABELSET_FILENAME",
                "Cumulation-GraphGet.js",
                "__LABELSET_FULLPATH",
                "FILE://Users/steven/Code/retold/modules/utility/cumulation/source/graph/Cumulation-GraphGet.js",
                "__LABELSET_FORMAT",
                "javascript",
                "Default"
            ],
            "FSTAT": {
                "Size": 22023,
                "Created": "2024-12-13T15:43:46.972Z",
                "Modified": "2024-12-13T15:43:46.972Z",
                "Accessed": "2024-12-13T18:52:16.293Z",
                "Mode": 33188
            }
        },
        "URI~CONTENT~FILE://Users/steven/Code/retold/modules/utility/cumulation/test/Cumulation_tests.js": {
            "UUID": "d588c9e1-d299-47e9-861c-1fa241a0a565",
            "Type": "URI",
            "Hash": "URI~CONTENT~FILE://Users/steven/Code/retold/modules/utility/cumulation/test/Cumulation_tests.js",
            "Path": "FILE://Users/steven/Code/retold/modules/utility/cumulation/test/Cumulation_tests.js",
            "Location": "/Users/steven/Code/retold/modules/utility/cumulation/test",
            "Name": "Cumulation_tests.js",
            "MimeType": "application/javascript",
            "Nature": "application",
            "Format": "javascript",
            "Schema": "Default",
            "Content": false,
            "Labels": [
                "__LABELSET_TYPE",
                "FILE",
                "__LABELSET_ADDRESS",
                "test",
                "__LABELSET_NAME",
                "Cumulation",
                "tests",
                "__LABELSET_EXTENSION",
                ".js",
                "__LABELSET_FILENAME",
                "Cumulation_tests.js",
                "__LABELSET_FULLPATH",
                "FILE://Users/steven/Code/retold/modules/utility/cumulation/test/Cumulation_tests.js",
                "__LABELSET_FORMAT",
                "javascript",
                "Default"
            ],
            "FSTAT": {
                "Size": 2779,
                "Created": "2024-12-13T15:43:46.972Z",
                "Modified": "2024-12-13T15:43:46.972Z",
                "Accessed": "2024-12-13T18:52:16.293Z",
                "Mode": 33188
            }
        }
    },
    "RootFolder": "/Users/steven/Code/retold/modules/utility/cumulation",
    "OutputFolderPath": "/Users/steven/Code/retold/modules/utility/cumulation/dist",
    "StageFolderPath": "/Users/steven/Code/retold/modules/utility/cumulation/dist/indoctrinate_content_staging",
    "TargetFilter": false,
    "WriteCatalogFile": true,
    "IgnoreUnknownTypes": false
}